jsonic/__init__.py
jsonic/decorators.py
jsonic/default_serializers.py
jsonic/exceptions.py
jsonic/pydantic_support.py
jsonic/serializable.py
jsonic/set_serializer.py
jsonic/tuple_serializer.py
jsonic/type_resolver.py
jsonic/util.py
jsonic/resolvers/__init__.py
jsonic/resolvers/dataclass_resolver.py
jsonic/resolvers/typehinted_resolver.py
py_jsonic-1.0.1.dist-info/licenses/LICENSE
tests/__init__.py
tests/conftest.py
tests/edge_cases/__init__.py
tests/edge_cases/test_edge_cases.py
tests/serialization/__init__.py
tests/serialization/test_basic_usage.py
tests/serialization/test_complex_usage.py
tests/serialization/mock/__init__.py
tests/serialization/mock/mock_data.py
tests/serialization/model/__init__.py
tests/serialization/model/main_model.py
tests/serialization/model/model.py
tests/unit/__init__.py
tests/unit/test_cross_feature_integration.py
tests/unit/test_custom_serializers.py
tests/unit/test_dataclass_support.py
tests/unit/test_deserialization.py
tests/unit/test_enum_support.py
tests/unit/test_error_context.py
tests/unit/test_error_handling.py
tests/unit/test_partial_serialization.py
tests/unit/test_pydantic_integration.py
tests/unit/test_register_type.py
tests/unit/test_serialization.py
tests/unit/test_set_support.py
tests/unit/test_slots_support.py
tests/unit/test_thread_safety.py
tests/unit/test_tuple_support.py
tests/unit/test_type_hints.py
tests/unit/test_type_not_found_errors.py
tests/unit/test_type_resolver_edge_cases.py
tests/unit/test_type_resolver_integration.py
tests/unit/test_varargs_support.py
py_jsonic-1.0.1.dist-info/METADATA
py_jsonic-1.0.1.dist-info/WHEEL
py_jsonic-1.0.1.dist-info/top_level.txt
py_jsonic-1.0.1.dist-info/RECORD
