Metadata-Version: 2.4
Name: py-jsonic
Version: 1.0.1
Summary: lightweight utility for JSON serialization
Home-page: https://github.com/OrrBin/Jsonic
Author: Orr Benyamini
Author-email: orrbenyamini@gmail.com
Classifier: Programming Language :: Python :: 3
Classifier: License :: OSI Approved :: MIT License
Classifier: Operating System :: OS Independent
Requires-Python: >=3.6
License-File: LICENSE
Dynamic: author
Dynamic: author-email
Dynamic: classifier
Dynamic: description
Dynamic: description-content-type
Dynamic: home-page
Dynamic: license-file
Dynamic: requires-python
Dynamic: summary
